gavel/__init__.py
gavel/__main__.py
gavel/cli.py
gavel/config/__init__.py
gavel/config/settings.py
gavel/dialects/__init__.py
gavel/dialects/base/__init__.py
gavel/dialects/base/compiler.py
gavel/dialects/base/dialect.py
gavel/dialects/base/parser.py
gavel/dialects/tptp/__init__.py
gavel/dialects/tptp/compiler.py
gavel/dialects/tptp/dialect.py
gavel/dialects/tptp/parser.py
gavel/dialects/tptp/tptp.lark
gavel/logic/__init__.py
gavel/logic/logic.py
gavel/logic/logic_utils.py
gavel/logic/problem.py
gavel/logic/solution.py
gavel/logic/sources.py
gavel/logic/status.py
gavel/plugins/__init__.py
gavel/prover/__init__.py
gavel/prover/registry.py
gavel/prover/base/__init__.py
gavel/prover/base/interface.py
gavel/prover/eprover/__init__.py
gavel/prover/eprover/interface.py
gavel/prover/hets/__init__.py
gavel/prover/hets/interface.py
gavel/prover/vampire/__init__.py
gavel/prover/vampire/interface.py
gavel/selection/__init__.py
gavel/selection/selector.py
gavel-0.1.7.dist-info/licenses/AUTHORS.rst
gavel-0.1.7.dist-info/licenses/LICENSE
gavel-0.1.7.dist-info/METADATA
gavel-0.1.7.dist-info/WHEEL
gavel-0.1.7.dist-info/top_level.txt
gavel-0.1.7.dist-info/RECORD
